core_pytorch_utils-1.0.4.data/data/requirements.txt
cpu/__init__.py
cpu/config_parser.py
cpu/distributed.py
cpu/history_buffer.py
cpu/logger.py
cpu/lr_scheduler.py
cpu/misc.py
cpu/trainer.py
cpu/hooks/__init__.py
cpu/hooks/checkpoint_hook.py
cpu/hooks/distributed_hook.py
cpu/hooks/eval_hook.py
cpu/hooks/hookbase.py
cpu/hooks/logger_hook.py
cpu/hooks/lr_update_hook.py
tests/__init__.py
tests/test_config_parser.py
tests/test_history_buffer.py
tests/test_lr_scheduler.py
tests/test_minist_training.py
tests/test_trainer.py
core_pytorch_utils-1.0.4.dist-info/LICENSE
core_pytorch_utils-1.0.4.dist-info/METADATA
core_pytorch_utils-1.0.4.dist-info/WHEEL
core_pytorch_utils-1.0.4.dist-info/top_level.txt
core_pytorch_utils-1.0.4.dist-info/RECORD
