Metadata-Version: 2.1
Name: core-pytorch-utils
Version: 1.0.4
Summary: Core APIs for deep learning.
Home-page: https://github.com/serend1p1ty/core-pytorch-utils
Author: serend1p1ty
Author-email: zjli1997@163.com
License: MIT License
Platform: UNKNOWN
License-File: LICENSE
Requires-Dist: torch (>1.6)
Requires-Dist: numpy
Requires-Dist: pyyaml
Requires-Dist: tabulate
Requires-Dist: termcolor
Requires-Dist: tensorboard
Requires-Dist: protobuf (~=3.19.0)
